Metadata-Version: 2.4
Name: treewalker
Version: 0.2.1
Summary: A simple package to walk a directory tree and collect files and sizes into a SQLite DB.
Home-page: https://gitlab.com/bmt-aus/tool/treewalker.git
Author: BMT Commercial Australia Pty Ltd, Jaap van der Velde
Author-email: jaap.vandervelde@bmtglobal.com
License: MIT
Project-URL: Home page, https://pypi.org/project/treewalker
Project-URL: Source Code, https://github.com/jaapvandervelde/treewalker
Project-URL: Documentation, https://treewalker.readthedocs.io/
Keywords: system,tool,database
Classifier: Development Status :: 4 - Beta
Classifier: Intended Audience :: Developers
Classifier: License :: OSI Approved :: MIT License
Classifier: Programming Language :: Python :: 3.4
License-File: LICENSE
Requires-Dist: conffu>=2.2.16
Requires-Dist: scandir
Requires-Dist: typing
Provides-Extra: dev
Requires-Dist: mkdocs; extra == "dev"
Requires-Dist: pymdown-extensions; extra == "dev"
Dynamic: author
Dynamic: author-email
Dynamic: classifier
Dynamic: description
Dynamic: description-content-type
Dynamic: home-page
Dynamic: keywords
Dynamic: license
Dynamic: license-file
Dynamic: project-url
Dynamic: provides-extra
Dynamic: requires-dist
Dynamic: summary
